{"_type":"export","__export_format":4,"__export_date":"2020-08-23T04:45:13.428Z","__export_source":"insomnia.desktop.app:v2020.3.3","resources":[{"_id":"req_3cb54d9353af4a0c8192956927e9cf60","authentication":{},"body":{},"created":1598157853013,"description":"","headers":[],"isPrivate":false,"metaSortKey":-1598061213518,"method":"GET","modified":1598157853013,"name":"Listar Comentario","parameters":[],"parentId":"fld_7548366f10a24bd2becec4b2d4210efe","settingDisableRenderRequestBody":false,"settingEncodeUrl":true,"settingFollowRedirects":"global","settingRebuildPath":true,"settingSendCookies":true,"settingStoreCookies":true,"url":"localhost:8080/ordens-servico/6/comentarios","_type":"request"},{"_id":"fld_7548366f10a24bd2becec4b2d4210efe","created":1598157853008,"description":"","environment":{},"environmentPropertyOrder":null,"metaSortKey":-1598156747893,"modified":1598157853008,"name":"Comentario","parentId":"fld_bd1ad0a792f04da2a9293e9bb6437763","_type":"request_group"},{"_id":"fld_bd1ad0a792f04da2a9293e9bb6437763","created":1598157852976,"description":"","environment":{},"environmentPropertyOrder":null,"metaSortKey":-1000000000,"modified":1598157853049,"name":"SpringCurso","parentId":"wrk_44f373f1adf445ee822d87094ec8a34b","_type":"request_group"},{"_id":"wrk_44f373f1adf445ee822d87094ec8a34b","created":1598157807779,"description":"","modified":1598157807779,"name":"Spring","parentId":null,"scope":null,"_type":"workspace"},{"_id":"req_115b11490d5c4709bc3e94e1b626ebf3","authentication":{},"body":{"mimeType":"application/json","text":"{\n\t\"descricao\":\"Está quase pronto\"\n}"},"created":1598157853010,"description":"","headers":[{"id":"pair_55029d7e6cb04282a0ebf86350fe8e7b","name":"Content-Type","value":"application/json"}],"isPrivate":false,"metaSortKey":-1598061213468,"method":"POST","modified":1598157853010,"name":"Comentario","parameters":[],"parentId":"fld_7548366f10a24bd2becec4b2d4210efe","settingDisableRenderRequestBody":false,"settingEncodeUrl":true,"settingFollowRedirects":"global","settingRebuildPath":true,"settingSendCookies":true,"settingStoreCookies":true,"url":"localhost:8080/ordens-servico/7/comentarios","_type":"request"},{"_id":"req_79ed9d029bf944fa8d70a3f985db1fd3","authentication":{},"body":{},"created":1598157853006,"description":"","headers":[],"isPrivate":false,"metaSortKey":-1598151355185,"method":"PUT","modified":1598157853006,"name":"Finalizar Ordem","parameters":[],"parentId":"fld_483331941b4247f586803a149d9897ee","settingDisableRenderRequestBody":false,"settingEncodeUrl":true,"settingFollowRedirects":"global","settingRebuildPath":true,"settingSendCookies":true,"settingStoreCookies":true,"url":"localhost:8080/ordens-servico/7/finalizacao","_type":"request"},{"_id":"fld_483331941b4247f586803a149d9897ee","created":1598157852995,"description":"","environment":{},"environmentPropertyOrder":null,"metaSortKey":-1597982810570,"modified":1598157852995,"name":"OrdemServico","parentId":"fld_bd1ad0a792f04da2a9293e9bb6437763","_type":"request_group"},{"_id":"req_6f6fdd3c49064e6093ac9a99bde744ff","authentication":{},"body":{"mimeType":"application/json","text":"{\n\t\"cliente\":{\n\t\t\"id\":111\n\t},\n\t\"descricao\":\"Melhoria notebook\",\n\t\"preco\": 55\n\n}"},"created":1598157852997,"description":"","headers":[{"id":"pair_f997141813914a05bf31e33d4662f413","name":"Content-Type","value":"application/json"}],"isPrivate":false,"metaSortKey":-1597982871350,"method":"POST","modified":1598157852997,"name":"Registro ordem Servico","parameters":[],"parentId":"fld_483331941b4247f586803a149d9897ee","settingDisableRenderRequestBody":false,"settingEncodeUrl":true,"settingFollowRedirects":"global","settingRebuildPath":true,"settingSendCookies":true,"settingStoreCookies":true,"url":"localhost:8080/ordens-servico","_type":"request"},{"_id":"req_1db9cd3f6fe24f269368d69fb096b091","authentication":{},"body":{"mimeType":"application/json","text":""},"created":1598157853001,"description":"","headers":[{"id":"pair_f997141813914a05bf31e33d4662f413","name":"Content-Type","value":"application/json"}],"isPrivate":false,"metaSortKey":-1597982840935,"method":"GET","modified":1598157853001,"name":"Listar ordem Servico","parameters":[],"parentId":"fld_483331941b4247f586803a149d9897ee","settingDisableRenderRequestBody":false,"settingEncodeUrl":true,"settingFollowRedirects":"global","settingRebuildPath":true,"settingSendCookies":true,"settingStoreCookies":true,"url":"localhost:8080/ordens-servico","_type":"request"},{"_id":"req_f72f44626933408f8ca8eae09e302658","authentication":{},"body":{"mimeType":"application/json","text":""},"created":1598157853003,"description":"","headers":[{"id":"pair_f997141813914a05bf31e33d4662f413","name":"Content-Type","value":"application/json"}],"isPrivate":false,"metaSortKey":-1597982825727.5,"method":"GET","modified":1598157853003,"name":"Buscar ordem Servico","parameters":[],"parentId":"fld_483331941b4247f586803a149d9897ee","settingDisableRenderRequestBody":false,"settingEncodeUrl":true,"settingFollowRedirects":"global","settingRebuildPath":true,"settingSendCookies":true,"settingStoreCookies":true,"url":"localhost:8080/ordens-servico/7","_type":"request"},{"_id":"req_dfe6e76ce567495d887ef6bd122eb147","authentication":{},"body":{"mimeType":"application/json","text":"{\n\t\"nome\":\"Fernando\",\n\t\"email\":\"fer@outlook.com.br\",\n\t\"telefone\":\"41996238262\"\n\t\n}"},"created":1598157852987,"description":"","headers":[{"id":"pair_1d3f132a164b4264be4d632b432d78d4","name":"Content-Type","value":"application/json"}],"isPrivate":false,"metaSortKey":-1597982810520,"method":"POST","modified":1598157852987,"name":"Registro de clientes","parameters":[],"parentId":"fld_b75e0d2cf1ec4f2fb03cf3175b6dad52","settingDisableRenderRequestBody":false,"settingEncodeUrl":true,"settingFollowRedirects":"global","settingRebuildPath":true,"settingSendCookies":true,"settingStoreCookies":true,"url":"localhost:8080/clientes","_type":"request"},{"_id":"fld_b75e0d2cf1ec4f2fb03cf3175b6dad52","created":1598157852979,"description":"","environment":{},"environmentPropertyOrder":null,"metaSortKey":-1597982810520,"modified":1598157852979,"name":"Cliente","parentId":"fld_bd1ad0a792f04da2a9293e9bb6437763","_type":"request_group"},{"_id":"req_b94baaecb0ef48b0a1226dbac4cb6d92","authentication":{},"body":{"mimeType":"application/json","text":"{\n\t\"nome\":\"Fernando De Paula\",\n\t\"email\":\"fer10@yahoo.com.br\",\n\t\"telefone\":\"41996238262\"\n\t\n}"},"created":1598157852990,"description":"","headers":[{"id":"pair_1d3f132a164b4264be4d632b432d78d4","name":"Content-Type","value":"application/json"}],"isPrivate":false,"metaSortKey":-1597982810495,"method":"PUT","modified":1598157852990,"name":"Atualizar clientes","parameters":[],"parentId":"fld_b75e0d2cf1ec4f2fb03cf3175b6dad52","settingDisableRenderRequestBody":false,"settingEncodeUrl":true,"settingFollowRedirects":"global","settingRebuildPath":true,"settingSendCookies":true,"settingStoreCookies":true,"url":"localhost:8080/clientes/10","_type":"request"},{"_id":"req_bb295009711541ebbc55f5320f0d3f46","authentication":{},"body":{},"created":1598157852983,"description":"","headers":[],"isPrivate":false,"metaSortKey":-1597982810482.5,"method":"GET","modified":1598157852983,"name":"Buscar clientes","parameters":[],"parentId":"fld_b75e0d2cf1ec4f2fb03cf3175b6dad52","settingDisableRenderRequestBody":false,"settingEncodeUrl":true,"settingFollowRedirects":"global","settingRebuildPath":true,"settingSendCookies":true,"settingStoreCookies":true,"url":"localhost:8080/clientes/10","_type":"request"},{"_id":"req_15d23bfbc9d54331be4cc9d9fa94da80","authentication":{},"body":{"mimeType":"application/json","text":""},"created":1598157852992,"description":"","headers":[{"id":"pair_1d3f132a164b4264be4d632b432d78d4","name":"Content-Type","value":"application/json"}],"isPrivate":false,"metaSortKey":-1597982810470,"method":"DELETE","modified":1598157852992,"name":"Deletar clientes","parameters":[],"parentId":"fld_b75e0d2cf1ec4f2fb03cf3175b6dad52","settingDisableRenderRequestBody":false,"settingEncodeUrl":true,"settingFollowRedirects":"global","settingRebuildPath":true,"settingSendCookies":true,"settingStoreCookies":true,"url":"localhost:8080/clientes/10","_type":"request"},{"_id":"env_f234f55a1584faddcf8423c198858f248c3f1d5a","color":null,"created":1598157807863,"data":{},"dataPropertyOrder":null,"isPrivate":false,"metaSortKey":1598157807863,"modified":1598157807863,"name":"Base Environment","parentId":"wrk_44f373f1adf445ee822d87094ec8a34b","_type":"environment"},{"_id":"jar_f234f55a1584faddcf8423c198858f248c3f1d5a","cookies":[],"created":1598157807867,"modified":1598157807867,"name":"Default Jar","parentId":"wrk_44f373f1adf445ee822d87094ec8a34b","_type":"cookie_jar"},{"_id":"spc_1e008bec225c49ebb1aa5cdaceb0fee3","contentType":"yaml","contents":"","created":1598157807788,"fileName":"Spring","modified":1598157807788,"parentId":"wrk_44f373f1adf445ee822d87094ec8a34b","_type":"api_spec"}]}